hypernets/__init__.py
hypernets/conf/__init__.py
hypernets/conf/_configuration.py
hypernets/core/__init__.py
hypernets/core/callbacks.py
hypernets/core/config.py
hypernets/core/context.py
hypernets/core/dispatcher.py
hypernets/core/meta_learner.py
hypernets/core/mutables.py
hypernets/core/objective.py
hypernets/core/ops.py
hypernets/core/pareto.py
hypernets/core/random_state.py
hypernets/core/search_space.py
hypernets/core/searcher.py
hypernets/core/stateful.py
hypernets/core/trial.py
hypernets/discriminators/__init__.py
hypernets/discriminators/_base.py
hypernets/discriminators/percentile.py
hypernets/dispatchers/__init__.py
hypernets/dispatchers/cfg.py
hypernets/dispatchers/in_process_dispatcher.py
hypernets/dispatchers/run.py
hypernets/dispatchers/run_broker.py
hypernets/dispatchers/run_predict.py
hypernets/dispatchers/run_predict_server.py
hypernets/dispatchers/cluster/__init__.py
hypernets/dispatchers/cluster/cluster.py
hypernets/dispatchers/cluster/driver_dispatcher.py
hypernets/dispatchers/cluster/executor_dispatcher.py
hypernets/dispatchers/cluster/grpc/__init__.py
hypernets/dispatchers/cluster/grpc/search_driver_client.py
hypernets/dispatchers/cluster/grpc/search_driver_service.py
hypernets/dispatchers/cluster/grpc/proto/__init__.py
hypernets/dispatchers/cluster/grpc/proto/spec_pb2.py
hypernets/dispatchers/cluster/grpc/proto/spec_pb2_grpc.py
hypernets/dispatchers/dask/__init__.py
hypernets/dispatchers/dask/dask_dispatcher.py
hypernets/dispatchers/predict/__init__.py
hypernets/dispatchers/predict/predict_helper.py
hypernets/dispatchers/predict/grpc/__init__.py
hypernets/dispatchers/predict/grpc/predict_client.py
hypernets/dispatchers/predict/grpc/predict_service.py
hypernets/dispatchers/predict/grpc/proto/__init__.py
hypernets/dispatchers/predict/grpc/proto/predict_pb2.py
hypernets/dispatchers/predict/grpc/proto/predict_pb2_grpc.py
hypernets/dispatchers/process/__init__.py
hypernets/dispatchers/process/grpc_process.py
hypernets-0.3.2.dist-info/LICENSE
hypernets-0.3.2.dist-info/METADATA
hypernets-0.3.2.dist-info/WHEEL
hypernets-0.3.2.dist-info/entry_points.txt
hypernets-0.3.2.dist-info/top_level.txt
hypernets-0.3.2.dist-info/RECORD
